pyie
