Metadata-Version: 1.0
Name: pyie
Version: 0.1.5
Summary: Validador de Inscrição Estadual para Python
Home-page: https://github.com/famoraes/pyie
Author: Fabiano Moraes
Author-email: fabiano.moraes@outlook.com
License: MIT
Keywords: python inscrição estadual ie
Platform: UNKNOWN
